Even Parity Generator and Checker/parity_checker.v
module parity_checker(c,p,x,y,z);
    output c;
    input x,y,z,p;

    assign c = x^y^z^p;
endmodule

Even Parity Generator and Checker/parity_checker_tb.v
`include "parity_checker.v"

module checker_tb();
    output c;
    reg x,y,z,p;
    parity_checker p1(c,p,x,y,z);
    initial
    begin
        x=1'b0; y=1'b0; z=1'b0; p=1'b1;
        #10 x=1'b0; y=1'b0; z=1'b1; p=1'b1;
        #10 x=1'b0; y=1'b1; z=1'b0; p=1'b0;
        #10 x=1'b0; y=1'b1; z=1'b1; p=1'b1;
        #10 x=1'b1; y=1'b0; z=1'b0; p=1'b1;
        #10 x=1'b1; y=1'b0; z=1'b1; p=1'b1;
        #10 x=1'b1; y=1'b1; z=1'b0; p=1'b0;
        #10 x=1'b1; y=1'b1; z=1'b1; p=1'b1;
    end
    initial
    begin
        $dumpfile("checker.vcd");
        $dumpvars(0, checker_tb);
    end
    initial
    begin
        $monitor("t = %3d x = %b y = %b z = %b p = %b c = %b \n ",$time, x, y, z, p, c);
    end
endmodule

Even Parity Generator and Checker/checker.vcd
$date
	Mon Oct 05 21:14:38 2020
$end
$version
	Icarus Verilog
$end
$timescale
	1s
$end
$scope module checker_tb $end
$var wire 1 ! c $end
$var reg 1 " p $end
$var reg 1 # x $end
$var reg 1 $ y $end
$var reg 1 % z $end
$scope module p1 $end
$var wire 1 ! c $end
$var wire 1 " p $end
$var wire 1 # x $end
$var wire 1 $ y $end
$var wire 1 % z $end
$upscope $end
$upscope $end
$enddefinitions $end
#0
$dumpvars
0%
0$
0#
1"
1!
$end
#10
0!
1%
#20
1!
0"
0%
1$
#30
1"
1%
#40
0!
0%
0$
1#
#50
1!
1%
#60
0!
0"
0%
1$
#70
1"
1%
