Even Parity Generator and Checker/even_parity.v
module even_pg (p,x,y,z);
    output p;
    input x,y,z;
    assign p = x^y^z;
endmodule

Even Parity Generator and Checker/even_parity_tb.v
`include "even_parity.v"

module even_parity_tb();
    output p;
    reg x,y,z;
    even_pg p1(p,x,y,z);
    initial
    begin
        x=1'b0; y=1'b0; z=1'b0;
        #10 x=1'b0; y=1'b0; z=1'b1;
        #10 x=1'b0; y=1'b1; z=1'b0;
        #10 x=1'b0; y=1'b1; z=1'b1;
        #10 x=1'b1; y=1'b0; z=1'b0;
        #10 x=1'b1; y=1'b0; z=1'b1;
        #10 x=1'b1; y=1'b1; z=1'b0;
        #10 x=1'b1; y=1'b1; z=1'b1;
    end
    initial
    begin
        $dumpfile("even_parity.vcd");
        $dumpvars(0, even_parity_tb);
    end
    initial
    begin
        $monitor("t = %3d x = %b y = %b z = %b p = %b \n ",$time, x, y, z, p);
    end
endmodule

Even Parity Generator and Checker/even_parity.vcd
$date
	Mon Oct 05 20:52:24 2020
$end
$version
	Icarus Verilog
$end
$timescale
	1s
$end
$scope module even_parity_tb $end
$var wire 1 ! p $end
$var reg 1 " x $end
$var reg 1 # y $end
$var reg 1 $ z $end
$scope module p1 $end
$var wire 1 ! p $end
$var wire 1 " x $end
$var wire 1 # y $end
$var wire 1 $ z $end
$upscope $end
$upscope $end
$enddefinitions $end
#0
$dumpvars
0$
0#
0"
0!
$end
#10
1!
1$
#20
0$
1#
#30
0!
1$
#40
1!
0$
0#
1"
#50
0!
1$
#60
0$
1#
#70
1!
1$
