Mod-16 Counter/counter.v
module counter (x,clk,reset,preload,load,count);
	input x,clk,reset,preload;
	input [3:0] load;
	output reg [3:0] count;

	reg [2:0] i=0;    // [23:0] i=0, for conversion of 30MHz clock to 1 MHz clock
	reg clkout=0;

	// New clock with time period of 10 Secs
	always@(negedge clk)
	begin
		i<=i+1;
		if(i==5)     // i==14705882 for conversion of 30MHz clock to 1MHz clock
		begin
			clkout <= ~clkout;
			i <= 0;
		end
	end

// mod-16 Counter Logic
	always@(posedge clkout, negedge reset)
	begin
		if(!reset)
			count<=0;
		else
		begin
			if(preload==1)
			begin
				count<=load;
				if (x==1)
				begin
					if(count==15)
						count<=0;
					else
						count<=count+1;
				end
				else
				begin
					if(count==0)
						count<=15;
					else
						count<=count-1;
				end
			end
			else if (x==1 && preload==0)
			begin
				if(count==15)
					count<=0;
				else
					count<=count+1;
			end
			else
			begin
				if(count==0)
					count<=15;
				else
					count<=count-1;
			end
		end
	end
endmodule

Mod-16 Counter/counter_tb.v
`include "counter.v"
module tb ();
	reg x,clk,reset,preload;
	reg [3:0] load;
	output [3:0] count;

	counter c1 (x,clk,reset,preload,load,count);
	initial
	begin
		clk = 1'b0;
		reset = 1'b1;
		#500 $finish;
	end
	always
		#0.5 clk = ~clk;
	initial
	begin
		#3 reset=0; preload = 0; load = 0; x = 0;
		#4 reset = 1; preload = 0; load = 0; x = 1;
		#200 preload = 0; load = 0; x = 0;
	end
	initial
	begin
        $dumpfile("counter.vcd");
        $dumpvars(0, tb);
    end
	initial
	begin
		$monitor("t = %3d preload = %b load = %b x = %b count = %b \n ", $time, preload, load, x, count);
	end
endmodule

Mod-16 Counter/counter.vcd
$date
	Fri Nov 13 00:31:18 2020
$end
$version
	Icarus Verilog
$end
$timescale
	1s
$end
$scope module tb $end
$var wire 4 ! count [3:0] $end
$var reg 1 " clk $end
$var reg 4 # load [3:0] $end
$var reg 1 $ preload $end
$var reg 1 % reset $end
$var reg 1 & x $end
$scope module c1 $end
$var wire 1 " clk $end
$var wire 4 ' load [3:0] $end
$var wire 1 $ preload $end
$var wire 1 % reset $end
$var wire 1 & x $end
$var reg 1 ( clkout $end
$var reg 4 ) count [3:0] $end
$var reg 3 * i [2:0] $end
$upscope $end
$upscope $end
$enddefinitions $end
#0
$dumpvars
b1 *
bx )
0(
bx '
x&
1%
x$
bx #
0"
bx !
$end
#1
1"
#2
b10 *
0"
#3
b0 !
b0 )
1"
0&
b0 #
b0 '
0$
0%
#4
b11 *
0"
#5
1"
#6
b100 *
0"
#7
1"
1&
1%
#8
b101 *
0"
#9
1"
#10
b1 !
b1 )
1(
b0 *
0"
#11
1"
#12
b1 *
0"
#13
1"
#14
b10 *
0"
#15
1"
#16
b11 *
0"
#17
1"
#18
b100 *
0"
#19
1"
#20
b101 *
0"
#21
1"
#22
0(
b0 *
0"
#23
1"
#24
b1 *
0"
#25
1"
#26
b10 *
0"
#27
1"
#28
b11 *
0"
#29
1"
#30
b100 *
0"
#31
1"
#32
b101 *
0"
#33
1"
#34
b10 !
b10 )
1(
b0 *
0"
#35
1"
#36
b1 *
0"
#37
1"
#38
b10 *
0"
#39
1"
#40
b11 *
0"
#41
1"
#42
b100 *
0"
#43
1"
#44
b101 *
0"
#45
1"
#46
0(
b0 *
0"
#47
1"
#48
b1 *
0"
#49
1"
#50
b10 *
0"
#51
1"
#52
b11 *
0"
#53
1"
#54
b100 *
0"
#55
1"
#56
b101 *
0"
#57
1"
#58
b11 !
b11 )
1(
b0 *
0"
#59
1"
#60
b1 *
0"
#61
1"
#62
b10 *
0"
#63
1"
#64
b11 *
0"
#65
1"
#66
b100 *
0"
#67
1"
#68
b101 *
0"
#69
1"
#70
0(
b0 *
0"
#71
1"
#72
b1 *
0"
#73
1"
#74
b10 *
0"
#75
1"
#76
b11 *
0"
#77
1"
#78
b100 *
0"
#79
1"
#80
b101 *
0"
#81
1"
#82
b100 !
b100 )
1(
b0 *
0"
#83
1"
#84
b1 *
0"
#85
1"
#86
b10 *
0"
#87
1"
#88
b11 *
0"
#89
1"
#90
b100 *
0"
#91
1"
#92
b101 *
0"
#93
1"
#94
0(
b0 *
0"
#95
1"
#96
b1 *
0"
#97
1"
#98
b10 *
0"
#99
1"
#100
b11 *
0"
#101
1"
#102
b100 *
0"
#103
1"
#104
b101 *
0"
#105
1"
#106
b101 !
b101 )
1(
b0 *
0"
#107
1"
#108
b1 *
0"
#109
1"
#110
b10 *
0"
#111
1"
#112
b11 *
0"
#113
1"
#114
b100 *
0"
#115
1"
#116
b101 *
0"
#117
1"
#118
0(
b0 *
0"
#119
1"
#120
b1 *
0"
#121
1"
#122
b10 *
0"
#123
1"
#124
b11 *
0"
#125
1"
#126
b100 *
0"
#127
1"
#128
b101 *
0"
#129
1"
#130
b110 !
b110 )
1(
b0 *
0"
#131
1"
#132
b1 *
0"
#133
1"
#134
b10 *
0"
#135
1"
#136
b11 *
0"
#137
1"
#138
b100 *
0"
#139
1"
#140
b101 *
0"
#141
1"
#142
0(
b0 *
0"
#143
1"
#144
b1 *
0"
#145
1"
#146
b10 *
0"
#147
1"
#148
b11 *
0"
#149
1"
#150
b100 *
0"
#151
1"
#152
b101 *
0"
#153
1"
#154
b111 !
b111 )
1(
b0 *
0"
#155
1"
#156
b1 *
0"
#157
1"
#158
b10 *
0"
#159
1"
#160
b11 *
0"
#161
1"
#162
b100 *
0"
#163
1"
#164
b101 *
0"
#165
1"
#166
0(
b0 *
0"
#167
1"
#168
b1 *
0"
#169
1"
#170
b10 *
0"
#171
1"
#172
b11 *
0"
#173
1"
#174
b100 *
0"
#175
1"
#176
b101 *
0"
#177
1"
#178
b1000 !
b1000 )
1(
b0 *
0"
#179
1"
#180
b1 *
0"
#181
1"
#182
b10 *
0"
#183
1"
#184
b11 *
0"
#185
1"
#186
b100 *
0"
#187
1"
#188
b101 *
0"
#189
1"
#190
0(
b0 *
0"
#191
1"
#192
b1 *
0"
#193
1"
#194
b10 *
0"
#195
1"
#196
b11 *
0"
#197
1"
#198
b100 *
0"
#199
1"
#200
b101 *
0"
#201
1"
#202
b1001 !
b1001 )
1(
b0 *
0"
#203
1"
#204
b1 *
0"
#205
1"
#206
b10 *
0"
#207
1"
0&
#208
b11 *
0"
#209
1"
#210
b100 *
0"
#211
1"
#212
b101 *
0"
#213
1"
#214
0(
b0 *
0"
#215
1"
#216
b1 *
0"
#217
1"
#218
b10 *
0"
#219
1"
#220
b11 *
0"
#221
1"
#222
b100 *
0"
#223
1"
#224
b101 *
0"
#225
1"
#226
b1000 !
b1000 )
1(
b0 *
0"
#227
1"
#228
b1 *
0"
#229
1"
#230
b10 *
0"
#231
1"
#232
b11 *
0"
#233
1"
#234
b100 *
0"
#235
1"
#236
b101 *
0"
#237
1"
#238
0(
b0 *
0"
#239
1"
#240
b1 *
0"
#241
1"
#242
b10 *
0"
#243
1"
#244
b11 *
0"
#245
1"
#246
b100 *
0"
#247
1"
#248
b101 *
0"
#249
1"
#250
b111 !
b111 )
1(
b0 *
0"
#251
1"
#252
b1 *
0"
#253
1"
#254
b10 *
0"
#255
1"
#256
b11 *
0"
#257
1"
#258
b100 *
0"
#259
1"
#260
b101 *
0"
#261
1"
#262
0(
b0 *
0"
#263
1"
#264
b1 *
0"
#265
1"
#266
b10 *
0"
#267
1"
#268
b11 *
0"
#269
1"
#270
b100 *
0"
#271
1"
#272
b101 *
0"
#273
1"
#274
b110 !
b110 )
1(
b0 *
0"
#275
1"
#276
b1 *
0"
#277
1"
#278
b10 *
0"
#279
1"
#280
b11 *
0"
#281
1"
#282
b100 *
0"
#283
1"
#284
b101 *
0"
#285
1"
#286
0(
b0 *
0"
#287
1"
#288
b1 *
0"
#289
1"
#290
b10 *
0"
#291
1"
#292
b11 *
0"
#293
1"
#294
b100 *
0"
#295
1"
#296
b101 *
0"
#297
1"
#298
b101 !
b101 )
1(
b0 *
0"
#299
1"
#300
b1 *
0"
#301
1"
#302
b10 *
0"
#303
1"
#304
b11 *
0"
#305
1"
#306
b100 *
0"
#307
1"
#308
b101 *
0"
#309
1"
#310
0(
b0 *
0"
#311
1"
#312
b1 *
0"
#313
1"
#314
b10 *
0"
#315
1"
#316
b11 *
0"
#317
1"
#318
b100 *
0"
#319
1"
#320
b101 *
0"
#321
1"
#322
b100 !
b100 )
1(
b0 *
0"
#323
1"
#324
b1 *
0"
#325
1"
#326
b10 *
0"
#327
1"
#328
b11 *
0"
#329
1"
#330
b100 *
0"
#331
1"
#332
b101 *
0"
#333
1"
#334
0(
b0 *
0"
#335
1"
#336
b1 *
0"
#337
1"
#338
b10 *
0"
#339
1"
#340
b11 *
0"
#341
1"
#342
b100 *
0"
#343
1"
#344
b101 *
0"
#345
1"
#346
b11 !
b11 )
1(
b0 *
0"
#347
1"
#348
b1 *
0"
#349
1"
#350
b10 *
0"
#351
1"
#352
b11 *
0"
#353
1"
#354
b100 *
0"
#355
1"
#356
b101 *
0"
#357
1"
#358
0(
b0 *
0"
#359
1"
#360
b1 *
0"
#361
1"
#362
b10 *
0"
#363
1"
#364
b11 *
0"
#365
1"
#366
b100 *
0"
#367
1"
#368
b101 *
0"
#369
1"
#370
b10 !
b10 )
1(
b0 *
0"
#371
1"
#372
b1 *
0"
#373
1"
#374
b10 *
0"
#375
1"
#376
b11 *
0"
#377
1"
#378
b100 *
0"
#379
1"
#380
b101 *
0"
#381
1"
#382
0(
b0 *
0"
#383
1"
#384
b1 *
0"
#385
1"
#386
b10 *
0"
#387
1"
#388
b11 *
0"
#389
1"
#390
b100 *
0"
#391
1"
#392
b101 *
0"
#393
1"
#394
b1 !
b1 )
1(
b0 *
0"
#395
1"
#396
b1 *
0"
#397
1"
#398
b10 *
0"
#399
1"
#400
b11 *
0"
#401
1"
#402
b100 *
0"
#403
1"
#404
b101 *
0"
#405
1"
#406
0(
b0 *
0"
#407
1"
#408
b1 *
0"
#409
1"
#410
b10 *
0"
#411
1"
#412
b11 *
0"
#413
1"
#414
b100 *
0"
#415
1"
#416
b101 *
0"
#417
1"
#418
b0 !
b0 )
1(
b0 *
0"
#419
1"
#420
b1 *
0"
#421
1"
#422
b10 *
0"
#423
1"
#424
b11 *
0"
#425
1"
#426
b100 *
0"
#427
1"
#428
b101 *
0"
#429
1"
#430
0(
b0 *
0"
#431
1"
#432
b1 *
0"
#433
1"
#434
b10 *
0"
#435
1"
#436
b11 *
0"
#437
1"
#438
b100 *
0"
#439
1"
#440
b101 *
0"
#441
1"
#442
b1111 !
b1111 )
1(
b0 *
0"
#443
1"
#444
b1 *
0"
#445
1"
#446
b10 *
0"
#447
1"
#448
b11 *
0"
#449
1"
#450
b100 *
0"
#451
1"
#452
b101 *
0"
#453
1"
#454
0(
b0 *
0"
#455
1"
#456
b1 *
0"
#457
1"
#458
b10 *
0"
#459
1"
#460
b11 *
0"
#461
1"
#462
b100 *
0"
#463
1"
#464
b101 *
0"
#465
1"
#466
b1110 !
b1110 )
1(
b0 *
0"
#467
1"
#468
b1 *
0"
#469
1"
#470
b10 *
0"
#471
1"
#472
b11 *
0"
#473
1"
#474
b100 *
0"
#475
1"
#476
b101 *
0"
#477
1"
#478
0(
b0 *
0"
#479
1"
#480
b1 *
0"
#481
1"
#482
b10 *
0"
#483
1"
#484
b11 *
0"
#485
1"
#486
b100 *
0"
#487
1"
#488
b101 *
0"
#489
1"
#490
b1101 !
b1101 )
1(
b0 *
0"
#491
1"
#492
b1 *
0"
#493
1"
#494
b10 *
0"
#495
1"
#496
b11 *
0"
#497
1"
#498
b100 *
0"
#499
1"
#500
b101 *
0"
