Two-One Multiplexer/two_one.v
// Gate Level
module mux_gate_level (i0,i1,s,out);
  input i0,i1,s;
  output out;
  wire s1,p,q;
  not a0(s1,s);
  and a1(p,s1,i0);
  and a2(q,s,i1);
  or a3(out,p,q);
endmodule

// Data_flow
module mux_data_flow (i0,i1,s,out);
  input i0,i1,s;
  output out;
  assign out = (~s & i0) | (s & i1);
endmodule 

// Behavioual
module mux_behavioual (i0,i1,s,out);
input i0,i1,s;
output out;
reg out;
always @ ( i0,i1,s ) 
begin
  if (s) 
    out = i1; 
  else
    out = i0;
end
endmodule

Two-One Multiplexer/2_1_tb.v
`include "2_1.v"
module two_one_tb ();
  reg s,i0,i1;
  wire out1,out2,out3;
  mux_gate_level m1(i0,i1,s,out1);
  mux_data_flow m2(i0,i1,s,out2);
  mux_behavioual m3(i0,i1,s,out3);
  initial
  begin
    $dumpfile("mux.vcd");
    $dumpvars(0, two_one_tb);
  end
  initial
  begin
    i0=0;i1=0;s=0;
    #10  i0=0;i1=0;s=1;
    #10  i0=0;i1=1;s=0;
    #10  i0=0;i1=1;s=1;
    #10  i0=1;i1=0;s=0;
    #10  i0=1;i1=0;s=1;
    #10  i0=1;i1=1;s=0;
    #10  i0=1;i1=1;s=1;
    #20 $finish;
  end
  initial begin
    $monitor("t=%3d i0=%b, i1=%b, s=%b, out1(gate level)=%b, out2(data flow)=%b, out3(behavioral)=%b",$time,i0,i1,s,out1,out2,out3);
  end
endmodule

Two-One Multiplexer/mux.vcd
$date
	Mon Oct 05 22:21:31 2020
$end
$version
	Icarus Verilog
$end
$timescale
	1s
$end
$scope module two_one_tb $end
$var wire 1 ! out3 $end
$var wire 1 " out2 $end
$var wire 1 # out1 $end
$var reg 1 $ i0 $end
$var reg 1 % i1 $end
$var reg 1 & s $end
$scope module m1 $end
$var wire 1 $ i0 $end
$var wire 1 % i1 $end
$var wire 1 # out $end
$var wire 1 ' p $end
$var wire 1 ( q $end
$var wire 1 & s $end
$var wire 1 ) s1 $end
$upscope $end
$scope module m2 $end
$var wire 1 $ i0 $end
$var wire 1 % i1 $end
$var wire 1 " out $end
$var wire 1 & s $end
$upscope $end
$scope module m3 $end
$var wire 1 $ i0 $end
$var wire 1 % i1 $end
$var wire 1 & s $end
$var reg 1 ! out $end
$upscope $end
$upscope $end
$enddefinitions $end
#0
$dumpvars
1)
0(
0'
0&
0%
0$
0#
0"
0!
$end
#10
0)
1&
#20
1)
0&
1%
#30
1#
1"
0)
1(
1!
1&
#40
1'
1#
1"
1)
0(
0&
0%
1$
#50
0#
0"
0'
0)
0!
1&
#60
1#
1"
1'
1)
1!
0&
1%
#70
0'
0)
1(
1&
