Vending Machine (FSM)/vending_mac.v
module vending_mac (output reg [1:0] z, input wire reset, clk, n, d, q, D);
	reg [2:0] current_state, next_state;
	parameter s0 = 3'b000, s1 = 3'b001, s2 = 3'b010, s3 = 3'b011, s4 = 3'b100, s5 = 3'b101, s6 = 3'b110;

	//STATE MEMORY
	always @ (posedge clk or negedge reset)
	begin
		if (!reset)
			current_state <= s0;
		else
			current_state <= next_state;
	end

	//NEXT STATE LOGIC
	// n-Nickel, d-Dime, q-Quarter, D-Done
	always @ (current_state or n or d or q or D)
	begin
		case (current_state)
			s0: if(n) next_state=s1; else if(d) next_state=s2; else if(q) next_state=s5;
			s1: if(n) next_state=s2; else if(d) next_state=s3; else if(q) next_state=s6;
			s2: if(D) next_state=s0; else if(n) next_state=s3; else if(d) next_state=s4; else if(q) next_state=s6;
			s3: if(D) next_state=s0; else if(n) next_state=s4; else if(d) next_state=s5; else if(q) next_state=s6;
			s4: if(D) next_state=s0; else if(n) next_state=s5; else if(d) next_state=s6; else if(q) next_state=s6;
			s5: if(D) next_state=s0; else if(n) next_state=s6; else if(d) next_state=s6; else if(q) next_state=s6;
			s6: if(D) next_state=s0; else if(n) next_state=s6; else if(d) next_state=s6; else if(q) next_state=s6;
			default: next_state=s0;
		endcase
	end
	
	//OUTPUT LOGIC
	always @ (current_state or D)
	begin
		case (current_state)
			s2:if(D) z=2'b01;//pencil 
			s3:if(D) z=2'b01;//pencil 
			s4:if(D) z=2'b10;//eraser 
			s5:if(D) z=2'b10;//eraser 
			s6:if(D) z=2'b11;//pen 
			default: z=2'b00;
		endcase
	end
endmodule

Vending Machine (FSM)/ven_tb.v
`include "vm.v"

module vm_tb();
	reg clk,reset,n,d,q,D;
	wire [1:0] z;
	vending_mac v1(z,reset,clk,n,d,q,D);

	always
		#10 clk = ~clk;
	initial
	begin
		$dumpfile("vending_mac.vcd");
		$dumpvars(0, vm_tb);
	end

	initial
	begin
		clk = 1'b0; reset = 1'b0; n=1'b0; d=1'b0; q=1'b0; D=1'b0;
		#0 reset = 1'b1;
		#6 n=1'b1; D=1'b1;
		#6 n=1'b0; D=1'b0;
		#15 q=1'b1;D=1'b1;
		#5 q=1'b0;D=1'b0;
		#15 d=1'b1;D=1'b1;
		#5 d=1'b0;D=1'b0;
		#15 n=1'b1;d=1'b1;D=1'b1;
		#5 n=1'b0;d=1'b0;D=1'b0;
		#15 n=1'b1;q=1'b1;D=1'b1;
		#5 n=1'b0;q=1'b0;D=1'b0;
		#20 $finish;
	end

	initial
	begin
	$monitor("t=%3d, n=%b, d=%b, q=%b, D=%b, z=%b",$time,n,d,q,D,z);
	end
endmodule

Vending Machine (FSM)/vending_mac.vcd
$date
	Wed Nov 04 00:26:02 2020
$end
$version
	Icarus Verilog
$end
$timescale
	1s
$end
$scope module vm_tb $end
$var wire 2 ! z [1:0] $end
$var reg 1 " D $end
$var reg 1 # clk $end
$var reg 1 $ d $end
$var reg 1 % n $end
$var reg 1 & q $end
$var reg 1 ' reset $end
$scope module v1 $end
$var wire 1 " D $end
$var wire 1 # clk $end
$var wire 1 $ d $end
$var wire 1 % n $end
$var wire 1 & q $end
$var wire 1 ' reset $end
$var reg 3 ( current_state [2:0] $end
$var reg 3 ) next_state [2:0] $end
$var reg 2 * z [1:0] $end
$upscope $end
$upscope $end
$enddefinitions $end
#0
$dumpvars
b0 *
b0 )
b0 (
1'
0&
0%
0$
0#
0"
b0 !
$end
#6
b1 )
1"
1%
#10
b10 )
b1 (
1#
#12
0"
0%
#20
0#
#27
b110 )
1"
1&
#30
b11 !
b11 *
b0 )
b110 (
1#
#32
0"
0&
#40
0#
#47
1"
1$
#50
b0 !
b0 *
b10 )
b0 (
1#
#52
0"
0$
#60
0#
#67
b1 )
1"
1$
1%
#70
b10 )
b1 (
1#
#72
0"
0$
0%
#80
0#
#87
1"
1&
1%
#90
b1 !
b1 *
b0 )
b10 (
1#
#92
0"
0&
0%
#100
0#
#110
b0 !
b0 *
b0 (
1#
