101 Sequence Detector/Mealy Non-Overlapping/mealy_no.v
module mealy_no (output reg z, input wire x, clk, reset);

	reg [1:0] current_state, next_state;
	parameter a = 2'b00, b = 2'b01, c = 2'b10;

	// State Memory
	always@ (posedge clk or negedge reset)
	begin
		if (!reset)
			current_state <= a;
		else
			current_state <= next_state;
	end

	// Next State Logic
	always@ (current_state or x)
	begin
		case(current_state)
			a: if(x == 1'b1) next_state = b; else next_state = a;
			b: if(x == 1'b1) next_state = b; else next_state = c;
			c: if(x == 1'b1) next_state = a; else next_state = a;
			default: next_state = a;
		endcase
	end

	// Output Logic
	always@ (current_state or x)
	begin
		case(current_state)
			a: if(x == 1'b1) z = 1'b0; else z = 1'b0;
			b: if(x == 1'b1) z = 1'b0; else z = 1'b0;
			c: if(x == 1'b1) z = 1'b1; else z = 1'b0;
			default: z = 1'b0;
		endcase
	end
endmodule

101 Sequence Detector/Mealy Non-Overlapping/mealy_no_tb.v
`include "mealy_no.v"
module mealy_no_tb ();
	reg x, clk, reset;
	output z;

	mealy_no m1(z,x,clk,reset);

	initial
	begin
		clk = 1'b0;
		x = 1'b0;
		reset = 1'b1;
		#100 $finish;
	end

	always
		#5 clk = ~clk;
	
	initial
	begin
		#10 x = 1'b1;
		#10 x = 1'b0;
		#10 x = 1'b1;
		#10 x = 1'b0;
		#10 x = 1'b1;
		#10 x = 1'b1;
		#10 x = 1'b0;
		#10 x = 1'b1;
	end

	initial 
    begin
        $dumpfile("mealy_no.vcd");
        $dumpvars(0, mealy_no_tb);
    end

	initial
    begin
        $monitor("t = %3d x = %b z = %b \n ", $time, x, z);
    end
endmodule

101 Sequence Detector/Mealy Non-Overlapping/mealy_no.vcd
$date
	Mon Oct 26 21:44:03 2020
$end
$version
	Icarus Verilog
$end
$timescale
	1s
$end
$scope module mealy_no_tb $end
$var wire 1 ! z $end
$var reg 1 " clk $end
$var reg 1 # reset $end
$var reg 1 $ x $end
$scope module m1 $end
$var wire 1 " clk $end
$var wire 1 # reset $end
$var wire 1 $ x $end
$var reg 2 % current_state [1:0] $end
$var reg 2 & next_state [1:0] $end
$var reg 1 ! z $end
$upscope $end
$upscope $end
$enddefinitions $end
#0
$dumpvars
b0 &
bx %
0$
1#
0"
0!
$end
#5
b0 %
1"
#10
b1 &
0"
1$
#15
b1 %
1"
#20
b10 &
0"
0$
#25
b0 &
b10 %
1"
#30
1!
0"
1$
#35
b1 &
0!
b0 %
1"
#40
b0 &
0"
0$
#45
1"
#50
b1 &
0"
1$
#55
b1 %
1"
#60
0"
#65
1"
#70
b10 &
0"
0$
#75
b0 &
b10 %
1"
#80
1!
0"
1$
#85
0!
b1 &
b0 %
1"
#90
0"
#95
b1 %
1"
